pipettewrapper/__init__.py
pipettewrapper/wrapper.py
pipettewrapper-0.0.3.dist-info/LICENSE
pipettewrapper-0.0.3.dist-info/METADATA
pipettewrapper-0.0.3.dist-info/WHEEL
pipettewrapper-0.0.3.dist-info/top_level.txt
pipettewrapper-0.0.3.dist-info/RECORD
