Metadata-Version: 2.1
Name: pipettewrapper
Version: 0.0.3
Summary: Wrapper to allow Opentrons multichannel pipettes to use any number of tips
Home-page: https://github.com/liamhawkins/PipetteWrapper
Author: Liam Hawkins
Author-email: liam.hawkins@carleton.ca
License: UNKNOWN
Platform: UNKNOWN
Classifier: Programming Language :: Python :: 3
Classifier: License :: OSI Approved :: GNU General Public License v3 (GPLv3)
Classifier: Operating System :: OS Independent
Classifier: Topic :: Scientific/Engineering
